dep_license/VERSION
dep_license/__init__.py
dep_license/__main__.py
dep_license/utils.py
dep_license-2.5.0.dist-info/LICENSE
dep_license-2.5.0.dist-info/METADATA
dep_license-2.5.0.dist-info/WHEEL
dep_license-2.5.0.dist-info/entry_points.txt
dep_license-2.5.0.dist-info/top_level.txt
dep_license-2.5.0.dist-info/RECORD
