Metadata-Version: 2.1
Name: dep-license
Version: 2.5.0
Summary: Report licenses information for dependencies in use by a Python project
Home-page: https://github.com/abduhbm/dep-license
Author: Abdulelah Bin Mahfoodh
License: MIT
Keywords: license check dependency package report
Platform: UNKNOWN
Classifier: Development Status :: 3 - Alpha
Classifier: Intended Audience :: Developers
Classifier: License :: OSI Approved :: MIT License
Classifier: Programming Language :: Python
Classifier: Programming Language :: Python :: 3
Classifier: Programming Language :: Python :: 3.6
Classifier: Programming Language :: Python :: 3.7
Classifier: Programming Language :: Python :: 3.8
Classifier: Programming Language :: Python :: 3.9
Classifier: Topic :: Utilities
Classifier: Topic :: System :: System Shells
License-File: LICENSE
Requires-Dist: tabulate
Requires-Dist: GitPython
Requires-Dist: toml
Requires-Dist: PyYAML
